{
  "algorithm": "dijkstra",
  "dataset": "national",
  "total_time": 60,
  "run_time": 60,
  "results": [
    {
      "run": 0,
      "score": 5164.33,
      "time": 0.5344531536102295
    },
    {
      "run": 1,
      "score": 5164.33,
      "time": 1.041621208190918
    },
    {
      "run": 2,
      "score": 5164.33,
      "time": 1.5613341331481934
    },
    {
      "run": 3,
      "score": 5164.33,
      "time": 2.0643742084503174
    },
    {
      "run": 4,
      "score": 5164.33,
      "time": 2.5650980472564697
    },
    {
      "run": 5,
      "score": 5164.33,
      "time": 3.0659801959991455
    },
    {
      "run": 6,
      "score": 5164.33,
      "time": 3.564244031906128
    },
    {
      "run": 7,
      "score": 5164.33,
      "time": 4.0641562938690186
    },
    {
      "run": 8,
      "score": 5164.33,
      "time": 4.596808195114136
    },
    {
      "run": 9,
      "score": 5164.33,
      "time": 5.095837354660034
    },
    {
      "run": 10,
      "score": 5164.33,
      "time": 5.59175705909729
    },
    {
      "run": 11,
      "score": 5164.33,
      "time": 6.0901572704315186
    },
    {
      "run": 12,
      "score": 5164.33,
      "time": 6.590639114379883
    },
    {
      "run": 13,
      "score": 5164.33,
      "time": 7.091707229614258
    },
    {
      "run": 14,
      "score": 5164.33,
      "time": 7.594824314117432
    },
    {
      "run": 15,
      "score": 5164.33,
      "time": 8.097795248031616
    },
    {
      "run": 16,
      "score": 5164.33,
      "time": 8.63476824760437
    },
    {
      "run": 17,
      "score": 5164.33,
      "time": 9.146374225616455
    },
    {
      "run": 18,
      "score": 5164.33,
      "time": 9.66641616821289
    },
    {
      "run": 19,
      "score": 5164.33,
      "time": 10.171184301376343
    },
    {
      "run": 20,
      "score": 5164.33,
      "time": 10.685781002044678
    },
    {
      "run": 21,
      "score": 5164.33,
      "time": 11.183761358261108
    },
    {
      "run": 22,
      "score": 5164.33,
      "time": 11.683901309967041
    },
    {
      "run": 23,
      "score": 5164.33,
      "time": 12.181575298309326
    },
    {
      "run": 24,
      "score": 5164.33,
      "time": 12.725479364395142
    },
    {
      "run": 25,
      "score": 5164.33,
      "time": 13.231545209884644
    },
    {
      "run": 26,
      "score": 5164.33,
      "time": 13.736929178237915
    },
    {
      "run": 27,
      "score": 5164.33,
      "time": 14.233818292617798
    },
    {
      "run": 28,
      "score": 5164.33,
      "time": 14.731458187103271
    },
    {
      "run": 29,
      "score": 5164.33,
      "time": 15.246069192886353
    },
    {
      "run": 30,
      "score": 5164.33,
      "time": 15.747809171676636
    },
    {
      "run": 31,
      "score": 5164.33,
      "time": 16.246875286102295
    },
    {
      "run": 32,
      "score": 5164.33,
      "time": 16.79577136039734
    },
    {
      "run": 33,
      "score": 5164.33,
      "time": 17.30274510383606
    },
    {
      "run": 34,
      "score": 5164.33,
      "time": 17.80276608467102
    },
    {
      "run": 35,
      "score": 5164.33,
      "time": 18.297723293304443
    },
    {
      "run": 36,
      "score": 5164.33,
      "time": 18.793772220611572
    },
    {
      "run": 37,
      "score": 5164.33,
      "time": 19.289635181427002
    },
    {
      "run": 38,
      "score": 5164.33,
      "time": 19.790433168411255
    },
    {
      "run": 39,
      "score": 5164.33,
      "time": 20.284334182739258
    },
    {
      "run": 40,
      "score": 5164.33,
      "time": 20.82152032852173
    },
    {
      "run": 41,
      "score": 5164.33,
      "time": 21.320274353027344
    },
    {
      "run": 42,
      "score": 5164.33,
      "time": 21.818074226379395
    },
    {
      "run": 43,
      "score": 5164.33,
      "time": 22.32472014427185
    },
    {
      "run": 44,
      "score": 5164.33,
      "time": 22.822864294052124
    },
    {
      "run": 45,
      "score": 5164.33,
      "time": 23.325311183929443
    },
    {
      "run": 46,
      "score": 5164.33,
      "time": 23.82396125793457
    },
    {
      "run": 47,
      "score": 5164.33,
      "time": 24.321378231048584
    },
    {
      "run": 48,
      "score": 5164.33,
      "time": 24.866820096969604
    },
    {
      "run": 49,
      "score": 5164.33,
      "time": 25.365833044052124
    },
    {
      "run": 50,
      "score": 5164.33,
      "time": 25.8973491191864
    },
    {
      "run": 51,
      "score": 5164.33,
      "time": 26.39694905281067
    },
    {
      "run": 52,
      "score": 5164.33,
      "time": 26.89654016494751
    },
    {
      "run": 53,
      "score": 5164.33,
      "time": 27.396015167236328
    },
    {
      "run": 54,
      "score": 5164.33,
      "time": 27.89459729194641
    },
    {
      "run": 55,
      "score": 5164.33,
      "time": 28.392553091049194
    },
    {
      "run": 56,
      "score": 5164.33,
      "time": 28.89183020591736
    },
    {
      "run": 57,
      "score": 5164.33,
      "time": 29.433632135391235
    },
    {
      "run": 58,
      "score": 5164.33,
      "time": 29.931013345718384
    },
    {
      "run": 59,
      "score": 5164.33,
      "time": 30.428121089935303
    },
    {
      "run": 60,
      "score": 5164.33,
      "time": 30.925211191177368
    },
    {
      "run": 61,
      "score": 5164.33,
      "time": 31.407103061676025
    },
    {
      "run": 62,
      "score": 5164.33,
      "time": 31.86506724357605
    },
    {
      "run": 63,
      "score": 5164.33,
      "time": 32.34435200691223
    },
    {
      "run": 64,
      "score": 5164.33,
      "time": 32.8471302986145
    },
    {
      "run": 65,
      "score": 5164.33,
      "time": 33.29791331291199
    },
    {
      "run": 66,
      "score": 5164.33,
      "time": 33.807512283325195
    },
    {
      "run": 67,
      "score": 5164.33,
      "time": 34.24925637245178
    },
    {
      "run": 68,
      "score": 5164.33,
      "time": 34.69599413871765
    },
    {
      "run": 69,
      "score": 5164.33,
      "time": 35.1676139831543
    },
    {
      "run": 70,
      "score": 5164.33,
      "time": 35.70255208015442
    },
    {
      "run": 71,
      "score": 5164.33,
      "time": 36.159980058670044
    },
    {
      "run": 72,
      "score": 5164.33,
      "time": 36.5981011390686
    },
    {
      "run": 73,
      "score": 5164.33,
      "time": 37.06005930900574
    },
    {
      "run": 74,
      "score": 5164.33,
      "time": 37.51877307891846
    },
    {
      "run": 75,
      "score": 5164.33,
      "time": 37.97647213935852
    },
    {
      "run": 76,
      "score": 5164.33,
      "time": 38.4145872592926
    },
    {
      "run": 77,
      "score": 5164.33,
      "time": 38.86872410774231
    },
    {
      "run": 78,
      "score": 5164.33,
      "time": 39.36398696899414
    },
    {
      "run": 79,
      "score": 5164.33,
      "time": 39.82723927497864
    },
    {
      "run": 80,
      "score": 5164.33,
      "time": 40.31273913383484
    },
    {
      "run": 81,
      "score": 5164.33,
      "time": 40.79499125480652
    },
    {
      "run": 82,
      "score": 5164.33,
      "time": 41.23351502418518
    },
    {
      "run": 83,
      "score": 5164.33,
      "time": 41.680992126464844
    },
    {
      "run": 84,
      "score": 5164.33,
      "time": 42.128106117248535
    },
    {
      "run": 85,
      "score": 5164.33,
      "time": 42.57717418670654
    },
    {
      "run": 86,
      "score": 5164.33,
      "time": 43.01593613624573
    },
    {
      "run": 87,
      "score": 5164.33,
      "time": 43.45359015464783
    },
    {
      "run": 88,
      "score": 5164.33,
      "time": 43.89806628227234
    },
    {
      "run": 89,
      "score": 5164.33,
      "time": 44.3438720703125
    },
    {
      "run": 90,
      "score": 5164.33,
      "time": 44.78739619255066
    },
    {
      "run": 91,
      "score": 5164.33,
      "time": 45.22495222091675
    },
    {
      "run": 92,
      "score": 5164.33,
      "time": 45.66917037963867
    },
    {
      "run": 93,
      "score": 5164.33,
      "time": 46.10715436935425
    },
    {
      "run": 94,
      "score": 5164.33,
      "time": 46.55435132980347
    },
    {
      "run": 95,
      "score": 5164.33,
      "time": 46.991249322891235
    },
    {
      "run": 96,
      "score": 5164.33,
      "time": 47.46748423576355
    },
    {
      "run": 97,
      "score": 5164.33,
      "time": 47.91076731681824
    },
    {
      "run": 98,
      "score": 5164.33,
      "time": 48.37807106971741
    },
    {
      "run": 99,
      "score": 5164.33,
      "time": 48.82070016860962
    },
    {
      "run": 100,
      "score": 5164.33,
      "time": 49.25920820236206
    },
    {
      "run": 101,
      "score": 5164.33,
      "time": 49.70068097114563
    },
    {
      "run": 102,
      "score": 5164.33,
      "time": 50.143280267715454
    },
    {
      "run": 103,
      "score": 5164.33,
      "time": 50.5874502658844
    },
    {
      "run": 104,
      "score": 5164.33,
      "time": 51.02643418312073
    },
    {
      "run": 105,
      "score": 5164.33,
      "time": 51.47037124633789
    },
    {
      "run": 106,
      "score": 5164.33,
      "time": 51.94593119621277
    },
    {
      "run": 107,
      "score": 5164.33,
      "time": 52.391433000564575
    },
    {
      "run": 108,
      "score": 5164.33,
      "time": 52.832932233810425
    },
    {
      "run": 109,
      "score": 5164.33,
      "time": 53.27685213088989
    },
    {
      "run": 110,
      "score": 5164.33,
      "time": 53.71733832359314
    },
    {
      "run": 111,
      "score": 5164.33,
      "time": 54.15629315376282
    },
    {
      "run": 112,
      "score": 5164.33,
      "time": 54.62240409851074
    },
    {
      "run": 113,
      "score": 5164.33,
      "time": 55.06631922721863
    },
    {
      "run": 114,
      "score": 5164.33,
      "time": 55.5157310962677
    },
    {
      "run": 115,
      "score": 5164.33,
      "time": 55.977429151535034
    },
    {
      "run": 116,
      "score": 5164.33,
      "time": 56.42346119880676
    },
    {
      "run": 117,
      "score": 5164.33,
      "time": 56.862526178359985
    },
    {
      "run": 118,
      "score": 5164.33,
      "time": 57.302168130874634
    },
    {
      "run": 119,
      "score": 5164.33,
      "time": 57.74838209152222
    },
    {
      "run": 120,
      "score": 5164.33,
      "time": 58.187833309173584
    },
    {
      "run": 121,
      "score": 5164.33,
      "time": 58.67084336280823
    },
    {
      "run": 122,
      "score": 5164.33,
      "time": 59.113903284072876
    },
    {
      "run": 123,
      "score": 5164.33,
      "time": 59.55680227279663
    },
    {
      "run": 124,
      "score": 5164.33,
      "time": 59.995909214019775
    },
    {
      "run": 125,
      "score": 5164.33,
      "time": 60.4390811920166
    }
  ]
}